.gitignore
COPYING
Makefile
README
pyproject.toml
setup.cfg
setup.py
btzen/__init__.py
btzen/_btzen.c
btzen/_btzen.pyx
btzen/_cm.c
btzen/_cm.pyx
btzen/_sd_bus.c
btzen/_sd_bus.pxd
btzen/_sd_bus.pyx
btzen/bluez.py
btzen/btweight.py
btzen/bus.py
btzen/cm.py
btzen/config.py
btzen/data.py
btzen/device.py
btzen/devio.py
btzen/error.py
btzen/py.typed
btzen/sensortag.py
btzen/serial.py
btzen/service.py
btzen/session.py
btzen/thingy52.py
btzen/util.py
btzen.egg-info/PKG-INFO
btzen.egg-info/SOURCES.txt
btzen.egg-info/dependency_links.txt
btzen.egg-info/requires.txt
btzen.egg-info/top_level.txt
btzen/tests/__init__.py
btzen/tests/test_device.py
doc/api.rst
doc/changelog.rst
doc/conf.py
doc/conf.rst
doc/index.rst
doc/power.rst
doc/use.rst
scripts/btzen-battery
scripts/btzen-cancel
scripts/btzen-connect
scripts/btzen-detect
scripts/btzen-interval
scripts/btzen-ostc
scripts/btzen-sensor-tag
scripts/btzen-service-impl
scripts/btzen-thingy52
scripts/btzen-type-check
scripts/btzen-weight