Metadata-Version: 2.1
Name: btzen
Version: 0.7.0
Summary: BTZen - library to asynchronously access Bluetooth devices
Home-page: https://github.com/wrobell/btzen
Author: Artur Wroblewski
Author-email: wrobell@riseup.net
License: GPLv3+
Platform: UNKNOWN
Classifier: Topic :: Software Development :: Libraries
Classifier: License :: OSI Approved :: GNU General Public License v3 or later (GPLv3+)
Classifier: Programming Language :: Python :: 3
Classifier: Development Status :: 4 - Beta
Requires-Python: >=3.9
Provides-Extra: tests
License-File: COPYING
